uipath_connectors/servicenow_servicenow/__init__.py
uipath_connectors/servicenow_servicenow/client.py
uipath_connectors/servicenow_servicenow/errors.py
uipath_connectors/servicenow_servicenow/py.typed
uipath_connectors/servicenow_servicenow/types.py
uipath_connectors/servicenow_servicenow/api/__init__.py
uipath_connectors/servicenow_servicenow/api/add_attachment/__init__.py
uipath_connectors/servicenow_servicenow/api/add_attachment/add_attachment.py
uipath_connectors/servicenow_servicenow/api/attachment_delete/__init__.py
uipath_connectors/servicenow_servicenow/api/attachment_delete/delete_attachment.py
uipath_connectors/servicenow_servicenow/api/attachment_download/__init__.py
uipath_connectors/servicenow_servicenow/api/attachment_download/download_attachment.py
uipath_connectors/servicenow_servicenow/api/attachment_get/__init__.py
uipath_connectors/servicenow_servicenow/api/attachment_get/list_all_attachment.py
uipath_connectors/servicenow_servicenow/api/attachment_getbyid/__init__.py
uipath_connectors/servicenow_servicenow/api/attachment_getbyid/get_attachment.py
uipath_connectors/servicenow_servicenow/api/curated_incident/__init__.py
uipath_connectors/servicenow_servicenow/api/curated_incident/create_new_incident.py
uipath_connectors/servicenow_servicenow/api/curated_incident/list_incidents.py
uipath_connectors/servicenow_servicenow/api/curated_incident/update_incident.py
uipath_connectors/servicenow_servicenow/api/curated_incident_task/__init__.py
uipath_connectors/servicenow_servicenow/api/curated_incident_task/create_incident_task.py
uipath_connectors/servicenow_servicenow/api/curated_incident_task/get_incident_task.py
uipath_connectors/servicenow_servicenow/api/curated_incident_task/list_incident_tasks.py
uipath_connectors/servicenow_servicenow/api/curated_incident_task/update_incident_task.py
uipath_connectors/servicenow_servicenow/api/curated_search_incident/__init__.py
uipath_connectors_servicenow_servicenow-1.2.5.dev12.dist-info/METADATA
uipath_connectors_servicenow_servicenow-1.2.5.dev12.dist-info/WHEEL
uipath_connectors_servicenow_servicenow-1.2.5.dev12.dist-info/entry_points.txt
uipath_connectors_servicenow_servicenow-1.2.5.dev12.dist-info/top_level.txt
uipath_connectors_servicenow_servicenow-1.2.5.dev12.dist-info/RECORD
